gdflowon/__about__.py
gdflowon/__init__.py
gdflowon/dag.py
gdflowon/identify.py
gdflowon/models.py
gdflowon/records.py
gdmetro_flowon-0.1.3.dist-info/LICENSE
gdmetro_flowon-0.1.3.dist-info/METADATA
gdmetro_flowon-0.1.3.dist-info/WHEEL
gdmetro_flowon-0.1.3.dist-info/top_level.txt
gdmetro_flowon-0.1.3.dist-info/RECORD
