Metadata-Version: 2.1
Name: gdmetro-flowon
Version: 0.1.3
Summary: An automated production tool provided by the GeneDock team.
Home-page: https://www.genedock.com
Author: GeneDock Contributor
Author-email: raomengnan@genedock.com
Maintainer: GeneDock Contributor
Maintainer-email: liming@genedock.com
License: UNKNOWN
Platform: Independent
Classifier: Development Status :: 4 - Beta
Classifier: Environment :: Console
Classifier: License :: OSI Approved :: Apache Software License
Classifier: Intended Audience :: Customer Service
Classifier: Intended Audience :: End Users/Desktop
Classifier: Operating System :: OS Independent
Classifier: Programming Language :: Python
